{
    "db": {
        "HOST": "production-database.cn2nj08ueeqy.ca-central-1.rds.amazonaws.com",
        "DB": "postgres",
        "UID": "ssh_company",
        "PWD": "vz45PtJbt2WfkebpXKPn",
        "PORT": 5432
    },
    "rabbit": {
        "protocol": "amqps",
        "hostname": "b-07fc57b8-c678-4d65-a4d7-431ed325eb7b.mq.ca-central-1.amazonaws.com",
        "port": 5671,
        "username": "ssh_company",
        "password": "A7FDH462HJD@3021",
        "locale": "en_US",
        "queue": "MessageQueue"
    },
    "s3": {
        "ID": "AKIA2G22WMUY3QTHDA2W",
        "SECRET": "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",
        "BUCKET_NAME": "cirkle-production",
        "REGION": "ca-central-1"
    }
}

